[
  {
    "documents": "일반건강검진·의료급여생애전환기검진: 일부항목 미실시 시 상담료 및 행정비용 삭감 기준",
    "metadatas": {
      "DYEAR": "2025",
      "MNTTL": "일반건강검진 삭감기준",
      "SBTTL": "일부항목 미실시",
      "TITLE": "2025년 건강검진 실시안내 책자",
      "ACCLV": "PUBLIC",
      "HSPCD": ""
    }
  },
  {
    "documents": "• 건강검진상담료 및 행정비용(신장·체중·비만도·시력·청력·혈압결과통보·입력·과거병력·생활습관·진찰소견·문진의사) 중 1항목 미실시 → 상담료 삭감",
    "metadatas": {
      "DYEAR": "2025",
      "MNTTL": "일반건강검진 삭감기준",
      "SBTTL": "상담료 삭감(기호1)",
      "TITLE": "2025년 건강검진 실시안내 책자",
      "ACCLV": "PUBLIC",
      "HSPCD": ""
    }
  },
  {
    "documents": "• 문진표 미첨부 또는 문진문항 미입력 시 → 상담료 삭감(기호2)",
    "metadatas": {
      "DYEAR": "2025",
      "MNTTL": "일반건강검진 삭감기준",
      "SBTTL": "문진표 삭감(기호2)",
      "TITLE": "2025년 건강검진 실시안내 책자",
      "ACCLV": "PUBLIC",
      "HSPCD": ""
    }
  },
  {
    "documents": "• 흉부방사선(필름14×14·14×17·CR·DR·Full PACS) 미실시 또는 사진불량 → 해당항목 삭감(기호26–29)",
    "metadatas": {
      "DYEAR": "2025",
      "MNTTL": "일반건강검진 삭감기준",
      "SBTTL": "흉부방사선 삭감(기호26-29)",
      "TITLE": "2025년 건강검진 실시안내 책자",
      "ACCLV": "PUBLIC",
      "HSPCD": ""
    }
  },
  {
    "documents": "• 요검사(요단백) 미실시 → 해당항목 삭감(기호3)",
    "metadatas": {
      "DYEAR": "2025",
      "MNTTL": "일반건강검진 삭감기준",
      "SBTTL": "요검사 삭감(기호3)",
      "TITLE": "2025년 건강검진 실시안내 책자",
      "ACCLV": "PUBLIC",
      "HSPCD": ""
    }
  },
  {
    "documents": "• 혈액검사(혈색소·공복혈당·총콜레스테롤·중성지방·HDL·AST·ALT·γ-GTP·크레아티닌·LDL) 중 1종목 미실시 → 해당항목 삭감(기호5–10,35,36,47,98)",
    "metadatas": {
      "DYEAR": "2025",
      "MNTTL": "일반건강검진 삭감기준",
      "SBTTL": "혈액검사 삭감(기호5-98)",
      "TITLE": "2025년 건강검진 실시안내 책자",
      "ACCLV": "PUBLIC",
      "HSPCD": ""
    }
  },
  {
    "documents": "• 판정 미입력 시 → 상담료 삭감(기호21)",
    "metadatas": {
      "DYEAR": "2025",
      "MNTTL": "일반건강검진 삭감기준",
      "SBTTL": "판정 삭감(기호21)",
      "TITLE": "2025년 건강검진 실시안내 책자",
      "ACCLV": "PUBLIC",
      "HSPCD": ""
    }
  },
  {
    "documents": "• 노인신체기능검사(낙상검사) 중 1종목 미실시 → 전체삭감(기호86)",
    "metadatas": {
      "DYEAR": "2025",
      "MNTTL": "일반건강검진 삭감기준",
      "SBTTL": "노인신체기능검사 전액삭감(기호86)",
      "TITLE": "2025년 건강검진 실시안내 책자",
      "ACCLV": "PUBLIC",
      "HSPCD": ""
    }
  },
  {
    "documents": "비대상자 건강진단실시(항원·항체·항체검사·골밀도·우울증·조기정신증·인지기능장애) → 해당항목 삭감(기호51–55,90–102,92–95,100–103,88,89)",
    "metadatas": {
      "DYEAR": "2025",
      "MNTTL": "단계별 검진 추가청구 환수",
      "SBTTL": "비대상자 실시 삭감",
      "TITLE": "2025년 건강검진 실시안내 책자",
      "ACCLV": "PUBLIC",
      "HSPCD": ""
    }
  },
  {
    "documents": "기준항목 미달실시: 검사 1–2개만 실시하거나 생활습관 상담결과가 양호인 경우 → 전액 또는 해당항목 삭감(기호58,59,77)",
    "metadatas": {
      "DYEAR": "2025",
      "MNTTL": "단계별 검진 추가청구 환수",
      "SBTTL": "기준항목 미달실시 삭감",
      "TITLE": "2025년 건강검진 실시안내 책자",
      "ACCLV": "PUBLIC",
      "HSPCD": ""
    }
  },
  {
    "documents": "기타: 상담의사교육 미수료 시 상담료 삭감(기호105), Full PACS 일부 위탁 시 차액 부과(기호30)",
    "metadatas": {
      "DYEAR": "2025",
      "MNTTL": "단계별 검진 추가청구 환수",
      "SBTTL": "기타 삭감·차액(기호30,105)",
      "TITLE": "2025년 건강검진 실시안내 책자",
      "ACCLV": "PUBLIC",
      "HSPCD": ""
    }
  },
  {
    "documents": "영유아건강검진: 기본진찰·신체계측·문진·발달평가·상담교육 미수·신체진찰소견 미기재 등 항목별 전액 또는 해당항목 삭감(기호1–3,91)",
    "metadatas": {
      "DYEAR": "2025",
      "MNTTL": "영유아건강검진 삭감기준",
      "SBTTL": "영유아건강검진 미실시 삭감",
      "TITLE": "2025년 건강검진 실시안내 책자",
      "ACCLV": "PUBLIC",
      "HSPCD": ""
    }
  },
  {
    "documents": "구강검진: 문진표·구강검사·치면세균막검사·문진문항·의사교육 미이수 시 전액 또는 해당항목 삭감(기호1–4)",
    "metadatas": {
      "DYEAR": "2025",
      "MNTTL": "구강검진 삭감기준",
      "SBTTL": "구강검진 미실시 삭감",
      "TITLE": "2025년 건강검진 실시안내 책자",
      "ACCLV": "PUBLIC",
      "HSPCD": ""
    }
  },
  {
    "documents": "영유아구강검진: 우식위험도평가·구강검사·의사교육 미이수 시 전액삭감(기호1,3)",
    "metadatas": {
      "DYEAR": "2025",
      "MNTTL": "영유아구강검진 삭감기준",
      "SBTTL": "영유아구강검진 미실시 삭감",
      "TITLE": "2025년 건강검진 실시안내 책자",
      "ACCLV": "PUBLIC",
      "HSPCD": ""
    }
  },
  {
    "documents": "공통사항: 지정제외후 청구·시효완성 시 전액삭감(기호96,97)",
    "metadatas": {
      "DYEAR": "2025",
      "MNTTL": "공통사항 삭감기준",
      "SBTTL": "공통사항 전액삭감",
      "TITLE": "2025년 건강검진 실시안내 책자",
      "ACCLV": "PUBLIC",
      "HSPCD": ""
    }
  },
  {
    "documents": "암검진: 위암 검사(위장조영검사·위내시경·조직검사) 미실시 또는 판독조건 불충분 시 해당항목 삭감(기호141,01,02)",
    "metadatas": {
      "DYEAR": "2025",
      "MNTTL": "암검진 삭감기준",
      "SBTTL": "위암 검사 삭감",
      "TITLE": "2025년 건강검진 실시안내 책자",
      "ACCLV": "PUBLIC",
      "HSPCD": ""
    }
  },
  {
    "documents": "암검진: 대장암 검사(내시경전처치4L·2L·354㎖·45.26g·1L·기타·조직검사) 미실시 또는 관찰소견 불충분 시 해당항목 삭감(기호04,07)",
    "metadatas": {
      "DYEAR": "2025",
      "MNTTL": "암검진 삭감기준",
      "SBTTL": "대장암 검사 삭감",
      "TITLE": "2025년 건강검진 실시안내 책자",
      "ACCLV": "PUBLIC",
      "HSPCD": ""
    }
  },
  {
    "documents": "암검진: 간암 검사(간초음파·혈청알파태아단백검사 일반·정밀·핵의학적) 중 1개만 실시 시 전액삭감(기호32,33,34,134)",
    "metadatas": {
      "DYEAR": "2025",
      "MNTTL": "암검진 삭감기준",
      "SBTTL": "간암 검사 전액삭감",
      "TITLE": "2025년 건강검진 실시안내 책자",
      "ACCLV": "PUBLIC",
      "HSPCD": ""
    }
  },
  {
    "documents": "암검진: 유방암 촬영(직촬4매·2매·CR·DR·Full PACS) 미실시 또는 판독조건 불충분 시 해당항목 삭감(기호143,144,147,139,140,145)",
    "metadatas": {
      "DYEAR": "2025",
      "MNTTL": "암검진 삭감기준",
      "SBTTL": "유방암 촬영 삭감",
      "TITLE": "2025년 건강검진 실시안내 책자",
      "ACCLV": "PUBLIC",
      "HSPCD": ""
    }
  },
  {
    "documents": "암검진: 폐암 검사(저선량흉부CT·사후결과상담) 미실시 또는 교육미이수 시 해당항목 삭감(기호87,88)",
    "metadatas": {
      "DYEAR": "2025",
      "MNTTL": "암검진 삭감기준",
      "SBTTL": "폐암 검사 삭감",
      "TITLE": "2025년 건강검진 실시안내 책자",
      "ACCLV": "PUBLIC",
      "HSPCD": ""
    }
  },
  {
    "documents": "암검진 상담·행정비용: 암종별 상담료 및 행정비용 미인정 시 상담료 삭감(기호41–46)",
    "metadatas": {
      "DYEAR": "2025",
      "MNTTL": "암검진 상담·판정",
      "SBTTL": "상담료 삭감(기호41-46)",
      "TITLE": "2025년 건강검진 실시안내 책자",
      "ACCLV": "PUBLIC",
      "HSPCD": ""
    }
  },
  {
    "documents": "암검진 상담기준 위반: 실시기준 외 검사·판정 미첨부 시 상담료·행정비용 삭감(기호51–57,61–67,81–86)",
    "metadatas": {
      "DYEAR": "2025",
      "MNTTL": "암검진 상담·판정",
      "SBTTL": "판정·문진표 미첨부 삭감",
      "TITLE": "2025년 건강검진 실시안내 책자",
      "ACCLV": "PUBLIC",
      "HSPCD": ""
    }
  },
  {
    "documents": "암검진 공통사항: 지정제외후 청구·시효완성 시 전액삭감(기호96,97)",
    "metadatas": {
      "DYEAR": "2025",
      "MNTTL": "암검진 공통사항",
      "SBTTL": "전액삭감(기호96,97)",
      "TITLE": "2025년 건강검진 실시안내 책자",
      "ACCLV": "PUBLIC",
      "HSPCD": ""
    }
  },
  {
    "documents": "암검진 기타: Full PACS 위탁 시 차액부과(기호145), 검사비용 차액(기호141)",
    "metadatas": {
      "DYEAR": "2025",
      "MNTTL": "암검진 기타",
      "SBTTL": "차액부과(기호141,145)",
      "TITLE": "2025년 건강검진 실시안내 책자",
      "ACCLV": "PUBLIC",
      "HSPCD": ""
    }
  }
]