[
  {
    "documents": "영유아 건강검진 안내 (2025년 기준)",
    "metadatas": {
      "DYEAR": "2025",
      "MNTTL": "영유아 건강검진",
      "SBTTL": "검진대상_건강보험가입자",
      "TITLE": "2025년 건강검진 실시안내 책자",
      "ACCLV": "PUBLIC",
      "HSPCD": ""
    }
  },
  {
    "documents": "건강보험가입자 및 신생아등록자 총계 대상자수 1,568,098명",
    "metadatas": {
      "DYEAR": "2025",
      "MNTTL": "영유아 건강검진",
      "SBTTL": "검진대상_총계",
      "TITLE": "2025년 건강검진 실시안내 책자",
      "ACCLV": "PUBLIC",
      "HSPCD": ""
    }
  },
  {
    "documents": "1차 건강검진: 생후 14일~35일 대상자수 14,424명",
    "metadatas": {
      "DYEAR": "2025",
      "MNTTL": "영유아 건강검진",
      "SBTTL": "1차_건강검진",
      "TITLE": "2025년 건강검진 실시안내 책자",
      "ACCLV": "PUBLIC",
      "HSPCD": ""
    }
  },
  {
    "documents": "2차 건강검진: 생후 4개월~6개월 대상자수 115,995명",
    "metadatas": {
      "DYEAR": "2025",
      "MNTTL": "영유아 건강검진",
      "SBTTL": "2차_건강검진",
      "TITLE": "2025년 건강검진 실시안내 책자",
      "ACCLV": "PUBLIC",
      "HSPCD": ""
    }
  },
  {
    "documents": "3차 건강검진: 생후 9개월~12개월 대상자수 226,575명",
    "metadatas": {
      "DYEAR": "2025",
      "MNTTL": "영유아 건강검진",
      "SBTTL": "3차_건강검진",
      "TITLE": "2025년 건강검진 실시안내 책자",
      "ACCLV": "PUBLIC",
      "HSPCD": ""
    }
  },
  {
    "documents": "4차 건강검진: 생후 18개월~24개월 대상자수 209,237명",
    "metadatas": {
      "DYEAR": "2025",
      "MNTTL": "영유아 건강검진",
      "SBTTL": "4차_건강검진",
      "TITLE": "2025년 건강검진 실시안내 책자",
      "ACCLV": "PUBLIC",
      "HSPCD": ""
    }
  },
  {
    "documents": "4차 구강검진: 생후 18개월~29개월 대상자수 209,237명",
    "metadatas": {
      "DYEAR": "2025",
      "MNTTL": "영유아 건강검진",
      "SBTTL": "4차_구강검진",
      "TITLE": "2025년 건강검진 실시안내 책자",
      "ACCLV": "PUBLIC",
      "HSPCD": ""
    }
  },
  {
    "documents": "5차 건강검진: 생후 30개월~36개월 대상자수 228,588명",
    "metadatas": {
      "DYEAR": "2025",
      "MNTTL": "영유아 건강검진",
      "SBTTL": "5차_건강검진",
      "TITLE": "2025년 건강검진 실시안내 책자",
      "ACCLV": "PUBLIC",
      "HSPCD": ""
    }
  },
  {
    "documents": "5차 구강검진: 생후 30개월~41개월 대상자수 228,588명",
    "metadatas": {
      "DYEAR": "2025",
      "MNTTL": "영유아 건강검진",
      "SBTTL": "5차_구강검진",
      "TITLE": "2025년 건강검진 실시안내 책자",
      "ACCLV": "PUBLIC",
      "HSPCD": ""
    }
  },
  {
    "documents": "6차 건강검진: 생후 42개월~48개월 대상자수 241,487명",
    "metadatas": {
      "DYEAR": "2025",
      "MNTTL": "영유아 건강검진",
      "SBTTL": "6차_건강검진",
      "TITLE": "2025년 건강검진 실시안내 책자",
      "ACCLV": "PUBLIC",
      "HSPCD": ""
    }
  },
  {
    "documents": "6차 구강검진: 생후 42개월~53개월 대상자수 241,487명",
    "metadatas": {
      "DYEAR": "2025",
      "MNTTL": "영유아 건강검진",
      "SBTTL": "6차_구강검진",
      "TITLE": "2025년 건강검진 실시안내 책자",
      "ACCLV": "PUBLIC",
      "HSPCD": ""
    }
  },
  {
    "documents": "7차 건강검진: 생후 54개월~60개월 대상자수 250,188명",
    "metadatas": {
      "DYEAR": "2025",
      "MNTTL": "영유아 건강검진",
      "SBTTL": "7차_건강검진",
      "TITLE": "2025년 건강검진 실시안내 책자",
      "ACCLV": "PUBLIC",
      "HSPCD": ""
    }
  },
  {
    "documents": "7차 구강검진: 생후 54개월~65개월 대상자수 250,188명",
    "metadatas": {
      "DYEAR": "2025",
      "MNTTL": "영유아 건강검진",
      "SBTTL": "7차_구강검진",
      "TITLE": "2025년 건강검진 실시안내 책자",
      "ACCLV": "PUBLIC",
      "HSPCD": ""
    }
  },
  {
    "documents": "8차 건강검진: 생후 66개월~71개월 대상자수 281,604명",
    "metadatas": {
      "DYEAR": "2025",
      "MNTTL": "영유아 건강검진",
      "SBTTL": "8차_건강검진",
      "TITLE": "2025년 건강검진 실시안내 책자",
      "ACCLV": "PUBLIC",
      "HSPCD": ""
    }
  },
  {
    "documents": "의료급여수급권자 1차~8차: 생후 14일부터 71개월까지 대상자수 12,645명",
    "metadatas": {
      "DYEAR": "2025",
      "MNTTL": "영유아 건강검진",
      "SBTTL": "의료급여수급권자",
      "TITLE": "2025년 건강검진 실시안내 책자",
      "ACCLV": "PUBLIC",
      "HSPCD": ""
    }
  },
  {
    "documents": "1차 검진 안내: 초기검진안내문 우편 또는 알림톡 매일 발송 (검진기간 종료 10일 전·5~9일 전 대상)",
    "metadatas": {
      "DYEAR": "2025",
      "MNTTL": "영유아 건강검진",
      "SBTTL": "검진안내_1차",
      "TITLE": "2025년 건강검진 실시안내 책자",
      "ACCLV": "PUBLIC",
      "HSPCD": ""
    }
  },
  {
    "documents": "2~8차 검진 안내: 검진표 디지털(매월 1~2일) 안내 후 미열람자 우편(매월 20~25일)",
    "metadatas": {
      "DYEAR": "2025",
      "MNTTL": "영유아 건강검진",
      "SBTTL": "검진안내_2~8차",
      "TITLE": "2025년 건강검진 실시안내 책자",
      "ACCLV": "PUBLIC",
      "HSPCD": ""
    }
  },
  {
    "documents": "검진표 분실·훼손·추가대상자: 대상자 확인서 발급",
    "metadatas": {
      "DYEAR": "2025",
      "MNTTL": "영유아 건강검진",
      "SBTTL": "검진안내_추가",
      "TITLE": "2025년 건강검진 실시안내 책자",
      "ACCLV": "PUBLIC",
      "HSPCD": ""
    }
  },
  {
    "documents": "홈페이지·모바일앱(The건강보험)에서 자녀(영유아) 검진대상 조회",
    "metadatas": {
      "DYEAR": "2025",
      "MNTTL": "영유아 건강검진",
      "SBTTL": "검진안내_조회",
      "TITLE": "2025년 건강검진 실시안내 책자",
      "ACCLV": "PUBLIC",
      "HSPCD": ""
    }
  },
  {
    "documents": "안내 대상 1: 검진대상자가 지역가입자인 경우 소속지사 = 세대주 관할지사",
    "metadatas": {
      "DYEAR": "2025",
      "MNTTL": "영유아 건강검진",
      "SBTTL": "안내대상_지역가입자",
      "ACCLV": "PUBLIC",
      "TITLE": "2025년 건강검진 실시안내 책자",
      "HSPCD": ""
    }
  },
  {
    "documents": "안내 대상 2: 검진대상자가 직장가입자 또는 피부양자인 경우 소속지사 = 직장가입자 소속지사",
    "metadatas": {
      "DYEAR": "2025",
      "MNTTL": "영유아 건강검진",
      "SBTTL": "안내대상_직장가입자",
      "TITLE": "2025년 건강검진 실시안내 책자",
      "ACCLV": "PUBLIC",
      "HSPCD": ""
    }
  },
  {
    "documents": "안내 대상 3: 검진대상자가 의료급여수급권자인 경우 소속지사 = 세대주 관할 보건소",
    "metadatas": {
      "DYEAR": "2025",
      "MNTTL": "영유아 건강검진",
      "SBTTL": "안내대상_의료급여",
      "TITLE": "2025년 건강검진 실시안내 책자",
      "ACCLV": "PUBLIC",
      "HSPCD": ""
    }
  },
  {
    "documents": "소속지사 구분: 지역가입자=주민등록 주소지 관할지사, 직장가입자·피부양자=직장가입자 소속지사, 신생아등록자=등록 시 보호자 소속지사, 의료급여수급권자=관할 시·군·구 보건소",
    "metadatas": {
      "DYEAR": "2025",
      "MNTTL": "영유아 건강검진",
      "SBTTL": "소속지사_구분",
      "TITLE": "2025년 건강검진 실시안내 책자",
      "ACCLV": "PUBLIC",
      "HSPCD": ""
    }
  },
  {
    "documents": "발송(디지털): 전자문서 시스템으로 매월 1~2일 디지털 안내 발송, 네이버앱 전자문서함 열람(실명ID 필수)",
    "metadatas": {
      "DYEAR": "2025",
      "MNTTL": "영유아 건강검진",
      "SBTTL": "발송_디지털",
      "TITLE": "2025년 건강검진 실시안내 책자",
      "ACCLV": "PUBLIC",
      "HSPCD": ""
    }
  },
  {
    "documents": "발송(우편): 디지털 미열람자 대상 매월 20~25일 우편발송, 주소 우선순위: 실거주지/송달지>행망주소지>등록거소지",
    "metadatas": {
      "DYEAR": "2025",
      "MNTTL": "영유아 건강검진",
      "SBTTL": "발송_우편",
      "TITLE": "2025년 건강검진 실시안내 책자",
      "ACCLV": "PUBLIC",
      "HSPCD": ""
    }
  },
  {
    "documents": "우편 주소 반영 시점: 초기검진안내문 생성 시, 대상자 확인서 발송 의뢰 시, 검진표·안내문 대상자 데이터 생성 시(매월 1일)",
    "metadatas": {
      "DYEAR": "2025",
      "MNTTL": "영유아 건강검진",
      "SBTTL": "발송_시점",
      "TITLE": "2025년 건강검진 실시안내 책자",
      "ACCLV": "PUBLIC",
      "HSPCD": ""
    }
  },
  {
    "documents": "대상자 구축(일 구축): 대상 = 6세 미만 신규 자격 취득자(건강보험가입자·의료급여수급권자), 구축일 = 자격취득 처리일 다음날",
    "metadatas": {
      "DYEAR": "2025",
      "MNTTL": "영유아 건강검진",
      "SBTTL": "대상자구축_일",
      "TITLE": "2025년 건강검진 실시안내 책자",
      "ACCLV": "PUBLIC",
      "HSPCD": ""
    }
  },
  {
    "documents": "대상자 구축(수시 구축): 수검 희망자·출생신고 전 신생아등록자(1차만) 자동 임시번호로 추가등록, 처리 다음날 임시번호 삭제",
    "metadatas": {
      "DYEAR": "2025",
      "MNTTL": "영유아 건강검진",
      "SBTTL": "대상자구축_수시",
      "TITLE": "2025년 건강검진 실시안내 책자",
      "ACCLV": "PUBLIC",
      "HSPCD": ""
    }
  },
  {
    "documents": "구축 제외: 국가정보원 가족(포털에서 조회·검진 가능), 의료급여수급권자 중 주소 미등록자(통보처 지정 불가)",
    "metadatas": {
      "DYEAR": "2025",
      "MNTTL": "영유아 건강검진",
      "SBTTL": "대상자구축_제외",
      "TITLE": "2025년 건강검진 실시안내 책자",
      "ACCLV": "PUBLIC",
      "HSPCD": ""
    }
  },
  {
    "documents": "일괄 연계 기준: 매년 1월1일, 기준 = 자격·보험료(전년11월), 연계 내용 = 소속지사·직역·통보처 등",
    "metadatas": {
      "DYEAR": "2025",
      "MNTTL": "영유아 건강검진",
      "SBTTL": "연계_일괄",
      "TITLE": "2025년 건강검진 실시안내 책자",
      "ACCLV": "PUBLIC",
      "HSPCD": ""
    }
  },
  {
    "documents": "수시 연계 기준: 자격처리일 다음날, 연계 항목 = 소속지사·증번호·가입자구분·관계·급여정지·출국(3개월 이상)·사망 등",
    "metadatas": {
      "DYEAR": "2025",
      "MNTTL": "영유아 건강검진",
      "SBTTL": "연계_수시",
      "TITLE": "2025년 건강검진 실시안내 책자",
      "ACCLV": "PUBLIC",
      "HSPCD": ""
    }
  },
  {
    "documents": "급여정지 처리: 사업연도 중 정지자 = 자격 연계하여 급여정지, 복귀자 = 자격 연계하여 해지",
    "metadatas": {
      "DYEAR": "2025",
      "MNTTL": "영유아 건강검진",
      "SBTTL": "급여정지",
      "TITLE": "2025년 건강검진 실시안내 책자",
      "ACCLV": "PUBLIC",
      "HSPCD": ""
    }
  }
]

